tlviz/__init__.py
tlviz/_module_utils.py
tlviz/_tl_utils.py
tlviz/_xarray_wrapper.py
tlviz/conftest.py
tlviz/data.py
tlviz/factor_tools.py
tlviz/model_evaluation.py
tlviz/multimodel_evaluation.py
tlviz/outliers.py
tlviz/postprocessing.py
tlviz/utils.py
tlviz/visualisation.py
tlviz/datasets/oslo_bike.nc4
TLViz-0.1.1.dist-info/LICENSE
TLViz-0.1.1.dist-info/METADATA
TLViz-0.1.1.dist-info/WHEEL
TLViz-0.1.1.dist-info/top_level.txt
TLViz-0.1.1.dist-info/RECORD
