Metadata-Version: 2.1
Name: TLViz
Version: 0.1.1
Summary: Package to visualise component-based decomposition models such as PCA and PARAFAC
Home-page: https://tensorly.org/viz
Author: Marie Roald & Yngve Mardal Moe
Author-email: roald.marie@gmail.com
License: "MIT license",
Platform: UNKNOWN
Classifier: Intended Audience :: Developers
Classifier: License :: OSI Approved :: MIT License
Classifier: Natural Language :: English
Classifier: Programming Language :: Python :: 3.7
Classifier: Programming Language :: Python :: 3.8
Classifier: Programming Language :: Python :: 3.9
Provides-Extra: docs
Provides-Extra: test
Provides-Extra: devel
Provides-Extra: all
